revcode/__init__.py
revcode/indic_normalizer.py
revcode/rev_code_joiner.py
revcode/revcode_conversion.py
revcode/revcode_helpers.py
revcode/mappings/__init__.py
revcode/mappings/assamese_to_rev.py
revcode/mappings/bengali_to_rev.py
revcode/mappings/gujarati_to_rev.py
revcode/mappings/hindi_to_rev.py
revcode/mappings/kannada_to_rev.py
revcode/mappings/malayalam_to_rev.py
revcode/mappings/marathi_to_rev.py
revcode/mappings/oriya_to_rev.py
revcode/mappings/punjabi_to_rev.py
revcode/mappings/rev_to_assamese.py
revcode/mappings/rev_to_bengali.py
revcode/mappings/rev_to_gujarati.py
revcode/mappings/rev_to_hindi.py
revcode/mappings/rev_to_kannada.py
revcode/mappings/rev_to_malayalam.py
revcode/mappings/rev_to_marathi.py
revcode/mappings/rev_to_oriya.py
revcode/mappings/rev_to_punjabi.py
revcode/mappings/rev_to_tamil.py
revcode/mappings/rev_to_telugu.py
revcode/mappings/tamil_to_rev.py
revcode/mappings/telugu_to_rev.py
revcode/meta/__init__.py
revcode/meta/enums.py
revcode/meta/mappings.py
revcode-3.dist-info/METADATA
revcode-3.dist-info/WHEEL
revcode-3.dist-info/licenses/LICENSE.txt
revcode-3.dist-info/RECORD
