Metadata-Version: 2.1
Name: revcode
Version: 3
Summary: A Roman encoding module for Indian languages
Project-URL: Homepage, https://github.com/reverieinc/revcode
Project-URL: Bug Tracker, https://github.com/reverieinc/revcode/issues
Author-email: Bhupen Chauhan <bhupen.chauhan@reverieinc.com>
License-File: LICENSE.txt
Keywords: Indian languages,Indic languages,Roman Encoding,revcode
Classifier: Intended Audience :: Developers
Classifier: License :: OSI Approved :: MIT License
Classifier: Operating System :: OS Independent
Classifier: Topic :: Software Development :: Libraries :: Python Modules
Requires-Python: >=3.5
